check/__init__.py
check/check.py
error/__init__.py
error/error.py
path/__init__.py
path/path.py
recorder/__init__.py
recorder/recorder.py
type/__init__.py
type/type.py
utils/__init__.py
utils/utils.py
ninstd-0.3.dist-info/LICENSE
ninstd-0.3.dist-info/METADATA
ninstd-0.3.dist-info/WHEEL
ninstd-0.3.dist-info/top_level.txt
ninstd-0.3.dist-info/RECORD
